auto_ds/__init__.py
auto_ds/autods.py
auto_ds/predictor.py
auto_ds/utils.py
auto_ds/models/__init__.py
auto_ds/models/catboost_method.py
auto_ds/models/catboost_utils.py
tests/__init__.py
auto_ds-0.0.1.dist-info/LICENSE
auto_ds-0.0.1.dist-info/METADATA
auto_ds-0.0.1.dist-info/WHEEL
auto_ds-0.0.1.dist-info/top_level.txt
auto_ds-0.0.1.dist-info/RECORD
