Metadata-Version: 2.1
Name: auto-ds
Version: 0.0.1
Summary: Auto Data Science Toolkit
Home-page: UNKNOWN
Author: Kaustuv.kunal@gmail.com
Author-email: <kaustuv.kunal@amail.com>
License: UNKNOWN
Keywords: pipeline optimization,hyperparameter optimization,data science,machine learning,evolutionary computation
Platform: UNKNOWN
Classifier: Development Status :: 3 - Alpha
Classifier: Programming Language :: Python :: 3
Classifier: Programming Language :: Python :: 3.7
License-File: LICENSE
Requires-Dist: catboost (>=0.25.1)
Requires-Dist: pandas (>=1.2.4)
Requires-Dist: optuna (>=2.9.1)
Requires-Dist: scikit-learn (>=1.0)
